sixe_idp/__init__.py
sixe_idp/api.py
6estates_idp-0.2.1.dist-info/METADATA
6estates_idp-0.2.1.dist-info/WHEEL
6estates_idp-0.2.1.dist-info/top_level.txt
6estates_idp-0.2.1.dist-info/RECORD
