Metadata-Version: 2.4
Name: 6estates-idp
Version: 0.2.1
Summary: Python SDK for IDP API by 6Estates Pte Ltd
Home-page: https://github.com/6estates/idp-python
Author: guosihan
Author-email: sihan.6estates@gmail.com
License: BSD 2-clause
Classifier: Programming Language :: Python :: 3.7
Classifier: Programming Language :: Python :: 3.8
Classifier: Programming Language :: Python :: 3.9
Requires-Dist: requests
Dynamic: author
Dynamic: author-email
Dynamic: classifier
Dynamic: description
Dynamic: home-page
Dynamic: license
Dynamic: requires-dist
Dynamic: summary
